educelab/hpc/__init__.py
educelab/hpc/apptainer.py
educelab/hpc/env.py
educelab/hpc/lmod.py
educelab/hpc/local.py
educelab/hpc/perf.py
educelab/hpc/semver.py
educelab/hpc/slurm.py
educelab_hpc-0.2.1.dist-info/licenses/LICENSE
educelab_hpc-0.2.1.dist-info/licenses/NOTICE
educelab_hpc-0.2.1.dist-info/METADATA
educelab_hpc-0.2.1.dist-info/WHEEL
educelab_hpc-0.2.1.dist-info/top_level.txt
educelab_hpc-0.2.1.dist-info/RECORD
